sql_blocks/__init__.py
sql_blocks/__main__.py
sql_blocks/sql_blocks.py
sql_blocks-1.20260106.dist-info/licenses/LICENSE
sql_blocks-1.20260106.dist-info/METADATA
sql_blocks-1.20260106.dist-info/WHEEL
sql_blocks-1.20260106.dist-info/top_level.txt
sql_blocks-1.20260106.dist-info/RECORD
