Metadata-Version: 2.4
Name: sql_blocks
Version: 1.20260106
Summary: Allows you to create objects for parts of SQL query commands. Also to combine these objects by joining them, adding or removing parts...
Home-page: https://github.com/julio-cascalles/sql_blocks
Author: Júlio Cascalles
Author-email: Julio Cascalles <julio.cascalles@outlook.com>
Project-URL: Homepage, https://github.com/julio-cascalles/sql_blocks
Classifier: Programming Language :: Python :: 3
Classifier: Operating System :: OS Independent
Requires-Python: >=3.8
License-File: LICENSE
Dynamic: author
Dynamic: home-page
Dynamic: license-file
